README.rst
setup.cfg
setup.py
citools/__init__.py
citools/data.py
citools.egg-info/PKG-INFO
citools.egg-info/SOURCES.txt
citools.egg-info/dependency_links.txt
citools.egg-info/pbr.json
citools.egg-info/requires.txt
citools.egg-info/top_level.txt
citools/jenkins/__init__.py
citools/jenkins/report.py
citools/maven/__init__.py
citools/maven/data.py
citools/maven/dependencies.py
citools/maven/pom.py
citools/persistence/__init__.py
citools/persistence/persistence.py
scripts/citools
scripts/export_job_state
scripts/merge_job_state
scripts/mvn_incremental
scripts/update_job_state
test/__init__.py
test/test_data.py
test/jenkins/__init__.py
test/jenkins/test_jenkins.py
test/maven/__init__.py
test/maven/test_dependencies.py
test/maven/test_pom.py
test/persistence/__init__.py
test/persistence/test_persistence.py